gpusitter/__init__.py
gpusitter/configs.py
gpusitter/emails.py
gpusitter/gpu.py
gpusitter/logger.py
gpusitter/main.py
gpusitter/utils.py
gpusitter-2.1.0.dist-info/WHEEL
gpusitter-2.1.0.dist-info/entry_points.txt
gpusitter-2.1.0.dist-info/METADATA
gpusitter-2.1.0.dist-info/RECORD
