Metadata-Version: 2.3
Name: gpusitter
Version: 2.1.0
Summary: Watch for idle GPUs and run your jobs: launches jobs in tmux, keeps logs/status and sends start/finish emails..
Author: Wilmer Wang
Author-email: Wilmer Wang <wangwei0206@foxmail.com>
Requires-Dist: nvidia-ml-py>=13.580.82
Requires-Dist: psutil>=7.0.0
Requires-Dist: rich>=14.1.0
Requires-Dist: tomli-w>=1.2.0
Maintainer: Wilmer Wang
Maintainer-email: Wilmer Wang <wangwei0206@foxmail.com>
Requires-Python: >=3.12
Project-URL: Homepage, https://github.com/wilmerwang/GPUSitter
